govsic/__init__.py
govsic/constants.py
govsic/exceptions.py
govsic/parser.py
govsic/sic.py
govsic/types.py
govsic/data/__init__.py
govsic/data/glossary.py
govsic/data/sections.py
govsic-1.1.5.dist-info/LICENSE
govsic-1.1.5.dist-info/METADATA
govsic-1.1.5.dist-info/WHEEL
govsic-1.1.5.dist-info/top_level.txt
govsic-1.1.5.dist-info/RECORD
